{
  "users": [
    {
      "firstName": "Bo",
      "lastName": "Ramirez",
      "email": "lusy@mailinator.com",
      "password": "Pa$$w0rd!",
      "id": "NIU4OT71fvw"
    },
    {
      "firstName": "Clark",
      "lastName": "Harrell",
      "email": "hopew@mailinator.com",
      "password": "Pa$$w0rd!",
      "id": "IUfbw8QFTvk"
    },
    {
      "firstName": "Renee",
      "lastName": "Rowe",
      "email": "vejew@mailinator.com",
      "password": "Pa$$w0rd!",
      "id": "AoFtkJYd_TY"
    },
    {
      "firstName": "Hannah",
      "lastName": "Day",
      "email": "dogedygo@mailinator.com",
      "password": "Pa$$w0rd!",
      "id": "_WSHN61UxaI"
    },
    {
      "firstName": "Dexter",
      "lastName": "Ellison",
      "email": "jahihixula@mailinator.com",
      "password": "Pa$$w0rd!",
      "id": "EKnaVxR9eVU"
    },
    {
      "firstName": "test",
      "lastName": "testt",
      "email": "test@test.com",
      "password": "nada123",
      "id": "rtxSScFdSYc"
    }
  ],
  "favoriteBooks": [
    {
      "userId": "EKnaVxR9eVU",
      "bookKey": "/works/OL27477543W",
      "title": "Angular Essentials",
      "author": "Dhananjay Kumar",
      "coverId": 13815624,
      "id": "bqTOtFag5XA"
    },
    {
      "userId": "EKnaVxR9eVU",
      "bookKey": "/works/OL5096257W",
      "title": "An introduction to mechanics",
      "author": "Daniel Kleppner",
      "coverId": 54475,
      "id": "tmZAkW4Nirg"
    },
    {
      "userId": "EKnaVxR9eVU",
      "bookKey": "/works/OL63996W",
      "title": "The Alhambra",
      "author": "Washington Irving",
      "coverId": 8237030,
      "id": "Bzuz5InR-jY"
    },
    {
      "userId": "EKnaVxR9eVU",
      "bookKey": "/works/OL1073561W",
      "title": "The Varieties of Religious Experience",
      "author": "Géré par OpenLibrary",
      "coverId": 2415434,
      "id": "KrtFqr5pUPU"
    },
    {
      "userId": "rtxSScFdSYc",
      "bookKey": "/works/OL19228543W",
      "title": "Notas de Liberdade (Em Portugues do Brasil)",
      "author": "Fred Elboni",
      "coverId": 8430397,
      "id": "PXB3PmaGFno"
    }
  ],
  "$schema": "./node_modules/json-server/schema.json"
}